mirtorch/__init__.py
mirtorch/alg/__init__.py
mirtorch/alg/cg.py
mirtorch/alg/fbpd.py
mirtorch/alg/fista.py
mirtorch/alg/pogm.py
mirtorch/alg/spectral.py
mirtorch/alg/util.py
mirtorch/dic/__init__.py
mirtorch/dic/soup.py
mirtorch/dic/util.py
mirtorch/linear/__init__.py
mirtorch/linear/basics.py
mirtorch/linear/linearmaps.py
mirtorch/linear/mri.py
mirtorch/linear/spect.py
mirtorch/linear/util.py
mirtorch/linear/wavelets.py
mirtorch/prox/__init__.py
mirtorch/prox/prox.py
mirtorch/vendors/pytorch_wavelets/__init__.py
mirtorch/vendors/pytorch_wavelets/_version.py
mirtorch/vendors/pytorch_wavelets/utils.py
mirtorch/vendors/pytorch_wavelets/dtcwt/__init__.py
mirtorch/vendors/pytorch_wavelets/dtcwt/coeffs.py
mirtorch/vendors/pytorch_wavelets/dtcwt/lowlevel.py
mirtorch/vendors/pytorch_wavelets/dtcwt/lowlevel2.py
mirtorch/vendors/pytorch_wavelets/dtcwt/transform2d.py
mirtorch/vendors/pytorch_wavelets/dtcwt/transform_funcs.py
mirtorch/vendors/pytorch_wavelets/dwt/__init__.py
mirtorch/vendors/pytorch_wavelets/dwt/lowlevel.py
mirtorch/vendors/pytorch_wavelets/dwt/swt_inverse.py
mirtorch/vendors/pytorch_wavelets/dwt/transform1d.py
mirtorch/vendors/pytorch_wavelets/dwt/transform2d.py
mirtorch/vendors/pytorch_wavelets/scatternet/__init__.py
mirtorch/vendors/pytorch_wavelets/scatternet/layers.py
mirtorch/vendors/pytorch_wavelets/scatternet/lowlevel.py
MIRTorch-0.1.2.dist-info/LICENSE
MIRTorch-0.1.2.dist-info/METADATA
MIRTorch-0.1.2.dist-info/WHEEL
MIRTorch-0.1.2.dist-info/entry_points.txt
MIRTorch-0.1.2.dist-info/top_level.txt
MIRTorch-0.1.2.dist-info/RECORD
