Metadata-Version: 2.1
Name: MIRTorch
Version: 0.1.2
Summary: a PyTorch-based image reconstruction toolbox
Author-email: Guanhua Wang <guanhuaw@umich.edu>
License: BSD-3-Clause
Project-URL: repository, https://github.com/guanhuaw/MIRTorch
Keywords: signal processing,inverse problems
Classifier: Programming Language :: Python :: 3
Classifier: License :: OSI Approved :: BSD License
Classifier: Operating System :: OS Independent
Classifier: Development Status :: 2 - Pre-Alpha
Classifier: Topic :: Scientific/Engineering :: Image Processing
Requires-Python: >=3.9
License-File: LICENSE
Requires-Dist: torch >=1.13
Requires-Dist: torchvision
Requires-Dist: torchkbnufft >=1.4.0
Requires-Dist: numpy >=1.24
Requires-Dist: dominate
Requires-Dist: scipy
Requires-Dist: PyWavelets
Requires-Dist: requests
Requires-Dist: einops
Requires-Dist: matplotlib
Requires-Dist: importlib-metadata ; python_version < "3.8"
Provides-Extra: dev
Requires-Dist: check-manifest ; extra == 'dev'
Provides-Extra: test
Requires-Dist: coverage ; extra == 'test'
Requires-Dist: pytest ; extra == 'test'
